positiveNegative/__init__.py
positiveNegative/myfuctions.py
positiveNegative-0.1.0.dist-info/METADATA
positiveNegative-0.1.0.dist-info/WHEEL
positiveNegative-0.1.0.dist-info/top_level.txt
positiveNegative-0.1.0.dist-info/RECORD
