Metadata-Version: 2.1
Name: positiveNegative
Version: 0.1.0
Summary: My first Python library
Home-page: UNKNOWN
Author: umesha ramesha hugger
Author-email: UNKNOWN
License: MIT
Platform: UNKNOWN
